causers-0.7.0.dist-info/METADATA
causers-0.7.0.dist-info/WHEEL
causers-0.7.0.dist-info/licenses/LICENSE
causers/__init__.py
causers/_causers.abi3.so
causers/_pandas_compat.py
causers-0.7.0.dist-info/RECORD
