Metadata-Version: 2.4
Name: causers
Version: 0.7.0
Classifier: Development Status :: 3 - Alpha
Classifier: Intended Audience :: Developers
Classifier: Intended Audience :: Science/Research
Classifier: License :: OSI Approved :: MIT License
Classifier: Programming Language :: Python :: 3
Classifier: Programming Language :: Python :: 3.8
Classifier: Programming Language :: Python :: 3.9
Classifier: Programming Language :: Python :: 3.10
Classifier: Programming Language :: Python :: 3.11
Classifier: Programming Language :: Python :: 3.12
Classifier: Programming Language :: Rust
Classifier: Topic :: Scientific/Engineering
Classifier: Topic :: Scientific/Engineering :: Mathematics
Requires-Dist: polars>=0.52
Requires-Dist: pandas>=2.0.0,<3.0.0 ; extra == 'pandas'
Requires-Dist: pyarrow>=10.0.0 ; extra == 'pandas'
Requires-Dist: pytest>=7.0 ; extra == 'dev'
Requires-Dist: pytest-cov>=4.0 ; extra == 'dev'
Requires-Dist: black>=23.0 ; extra == 'dev'
Requires-Dist: ruff>=0.1 ; extra == 'dev'
Requires-Dist: mypy>=1.0 ; extra == 'dev'
Requires-Dist: maturin>=1.4 ; extra == 'dev'
Requires-Dist: pandas>=2.0.0 ; extra == 'dev'
Requires-Dist: pyarrow>=10.0.0 ; extra == 'dev'
Requires-Dist: pytest>=7.0 ; extra == 'test'
Requires-Dist: pytest-cov>=4.0 ; extra == 'test'
Requires-Dist: numpy>=1.20 ; extra == 'test'
Requires-Dist: statsmodels>=0.14.0,<0.16.0 ; extra == 'test'
Requires-Dist: azcausal>=0.2 ; extra == 'test'
Requires-Dist: pysyncon>=1.0 ; extra == 'test'
Requires-Dist: pyfixest>=0.18 ; extra == 'test'
Requires-Dist: hypothesis>=6.0 ; extra == 'test'
Requires-Dist: pandas>=2.0.0 ; extra == 'test'
Requires-Dist: pyarrow>=10.0.0 ; extra == 'test'
Provides-Extra: pandas
Provides-Extra: dev
Provides-Extra: test
License-File: LICENSE
Summary: High-performance statistical operations for Polars DataFrames
Keywords: polars,statistics,regression,rust,performance
Author: James Nordlund
Requires-Python: >=3.8
Project-URL: Homepage, https://github.com/causers/causers
Project-URL: Repository, https://github.com/causers/causers
Project-URL: Issues, https://github.com/causers/causers/issues
